lt_utils/__init__.py
lt_utils/common.py
lt_utils/file_ops.py
lt_utils/logging_utils.py
lt_utils/math_ops.py
lt_utils/misc_utils.py
lt_utils/notebooks_utils.py
lt_utils/plots.py
lt_utils/text_ops.py
lt_utils/type_checks.py
lt_utils/_internal/texts/_unicode_symbols.py
lt_utils/_internal/texts/clean_up.py
lt_utils/_internal/texts/nlp_stuff.py
lt_utils/_internal/texts/requoter.py
lt_utils/torch_utils/__init__.py
lt_utils/torch_utils/tensor_ops.py
lt_utils/type_utils/__init__.py
lt_utils/type_utils/_cos_tp.py
lt_utils/type_utils/custom_types.py
lt_utils-0.2.0.4.dist-info/licenses/LICENSE
lt_utils-0.2.0.4.dist-info/METADATA
lt_utils-0.2.0.4.dist-info/WHEEL
lt_utils-0.2.0.4.dist-info/top_level.txt
lt_utils-0.2.0.4.dist-info/RECORD
