Metadata-Version: 2.4
Name: lt-utils
Version: 0.2.0.4
Summary: Collection of utilities for file, type, and basic logic handling across Python projects.
Home-page: https://github.com/gr1336/lt-utils/
Author: gr1336
License: Apache Software License (Apache-2.0)
Classifier: Development Status :: 1 - Planning
Classifier: Topic :: Software Development
Classifier: Topic :: Software Development :: Libraries
Classifier: Topic :: Utilities
License-File: LICENSE
Requires-Dist: numpy>=1.26.4
Requires-Dist: markdown2
Requires-Dist: markdownify
Requires-Dist: pyperclip>=1.8.2
Requires-Dist: textblob>=0.18.0
Requires-Dist: pyyaml>=6.0.0
Requires-Dist: nltk==3.9.*
Requires-Dist: scikit-learn>=1.4.0
Requires-Dist: spacy<4,>3.5
Requires-Dist: numba<0.70,>=0.60.0
Requires-Dist: pandas
Requires-Dist: plotly
Requires-Dist: torch
Dynamic: author
Dynamic: classifier
Dynamic: description
Dynamic: description-content-type
Dynamic: home-page
Dynamic: license
Dynamic: license-file
Dynamic: requires-dist
Dynamic: summary
